Metadata-Version: 2.4
Name: mcp-server-moralis-bacar
Version: 0.1.0
Summary: Add your description here
Requires-Python: >=3.12
Requires-Dist: build>=1.2.2.post1
Requires-Dist: dotenv>=0.9.9
Requires-Dist: httpx>=0.28.1
Requires-Dist: mcp[cli]>=1.6.0
Requires-Dist: moralis>=0.1.49
Requires-Dist: twine>=6.1.0
